borneo/__init__.py
borneo/device.py
borneo/esptouch.py
borneo/lyfi.py
borneoiot-0.1.0.dist-info/METADATA
borneoiot-0.1.0.dist-info/WHEEL
borneoiot-0.1.0.dist-info/top_level.txt
borneoiot-0.1.0.dist-info/RECORD
