Metadata-Version: 2.1
Name: borneoiot
Version: 0.1.0
Summary: A open-source Python client library for devices under the Borneo-IoT Project
Home-page: https://www.borneoiot.com
Author: Yunnan BinaryStars Technologies Co., Ltd.
Author-email: oldrev@gmail.com
License: GPL3.0+
Classifier: Programming Language :: Python :: 3
Classifier: Operating System :: OS Independent
Requires-Python: >=3.6
